frigg/__init__.py
frigg/api.py
frigg/config.py
frigg/defaults.yml
frigg/helpers.py
frigg/projects.py
frigg_common-0.2.0.dist-info/DESCRIPTION.rst
frigg_common-0.2.0.dist-info/METADATA
frigg_common-0.2.0.dist-info/metadata.json
frigg_common-0.2.0.dist-info/RECORD
frigg_common-0.2.0.dist-info/top_level.txt
frigg_common-0.2.0.dist-info/WHEEL
