Metadata-Version: 2.0
Name: frigg-common
Version: 0.2.0
Summary: Utils for frigg apps
Home-page: https://github.com/frigg/frigg-common
Author: The frigg team
Author-email: hi@frigg.io
License: MIT
Platform: UNKNOWN
Classifier: Programming Language :: Python
Requires-Dist: frigg-coverage
Requires-Dist: pyyaml
Requires-Dist: requests
